MANIFEST.in
README.rst
setup.py
pyort/__init__.py
pyort/__main__.py
pyort/pyort.py
pyort/pyort_fun.py
pyort.egg-info/PKG-INFO
pyort.egg-info/SOURCES.txt
pyort.egg-info/dependency_links.txt
pyort.egg-info/entry_points.txt
pyort.egg-info/requires.txt
pyort.egg-info/top_level.txt