Metadata-Version: 1.0
Name: pyort
Version: 0.1.8
Summary: Command line tool for monitoring all network connections
Home-page: https://github.com/Gananath/pyort
Author: Gananath R
Author-email: no-mail@no-mail.com
License: MIT
Platform: UNKNOWN
